SWE_Solver/__init__.py
SWE_Solver/examples.py
SWE_Solver/initial.py
SWE_Solver/post_processing.py
SWE_Solver/reconstruct.py
SWE_Solver/solver.py
SWE_Solver-0.1.7.dist-info/LICENSE
SWE_Solver-0.1.7.dist-info/METADATA
SWE_Solver-0.1.7.dist-info/WHEEL
SWE_Solver-0.1.7.dist-info/top_level.txt
SWE_Solver-0.1.7.dist-info/RECORD
