Metadata-Version: 2.1
Name: SWE_Solver
Version: 0.1.7
Summary: A small package including a one-dimensional well-balanced Shallow Water Equations solver.
Author-email: Daniel Cortild <d.cortild@rug.nl>
Project-URL: Homepage, https://github.com/DanielCortild/SWE-Solver
Project-URL: Bug Tracker, https://github.com/DanielCortild/SWE-Solver/issues
Classifier: Programming Language :: Python :: 3
Classifier: License :: OSI Approved :: MIT License
Classifier: Operating System :: OS Independent
Requires-Python: >=3.7
License-File: LICENSE
